f3_nation_data/__init__.py
f3_nation_data/analytics.py
f3_nation_data/database.py
f3_nation_data/fetch.py
f3_nation_data/transform.py
f3_nation_data/version.py
f3_nation_data/cli/__init__.py
f3_nation_data/cli/weekly_report.py
f3_nation_data/cli/templates/weekly_report.txt
f3_nation_data/models/__init__.py
f3_nation_data/models/beatdown_record.py
f3_nation_data/models/parsed/__init__.py
f3_nation_data/models/parsed/ao.py
f3_nation_data/models/parsed/beatdown.py
f3_nation_data/models/parsed/user.py
f3_nation_data/models/sql/__init__.py
f3_nation_data/models/sql/ao.py
f3_nation_data/models/sql/base.py
f3_nation_data/models/sql/beatdown.py
f3_nation_data/models/sql/user.py
f3_nation_data/parsing/__init__.py
f3_nation_data/parsing/backblast.py
f3_nation_data-0.0.3.dist-info/METADATA
f3_nation_data-0.0.3.dist-info/WHEEL
f3_nation_data-0.0.3.dist-info/entry_points.txt
f3_nation_data-0.0.3.dist-info/licenses/LICENSE
f3_nation_data-0.0.3.dist-info/RECORD
