Metadata-Version: 2.4
Name: f3-nation-data
Version: 0.0.3
Summary: library to extract, parse, and analyze F3 Nation SQL database data
Author: f3-noho
License-Expression: MIT
License-File: LICENSE
Requires-Python: >=3.11
Requires-Dist: jinja2>=3.1.6
Requires-Dist: pydantic<3,>=2.11.7
Requires-Dist: pymysql>=1.1.1
Requires-Dist: sqlalchemy>=2.0.43
Requires-Dist: structlog<26,>=25.4.0
